xdimer/__init__.py
xdimer/auxiliary.py
xdimer/quantummechanical.py
xdimer/semiclassical.py
xdimer/examples/__init__.py
xdimer/examples/fitting_emission_data/__init__.py
xdimer/examples/fitting_emission_data/__main__.py
xdimer/examples/simulating_emission/__init__.py
xdimer/examples/simulating_emission/__main__.py
XDimer-1.0.6.dist-info/LICENSE.md
XDimer-1.0.6.dist-info/METADATA
XDimer-1.0.6.dist-info/WHEEL
XDimer-1.0.6.dist-info/top_level.txt
XDimer-1.0.6.dist-info/RECORD
