Metadata-Version: 2.1
Name: XDimer
Version: 1.0.6
Summary: Simulation of multi-molecular emission spectra dominated by intermolecular vibrations 
Home-page: https://github.com/HammerSeb/xDimer
Author: Sebastian Hammer
Author-email: sebastian.hammer@mail.mcgill.ca
License: MIT
Requires-Python: >=3.6
License-File: LICENSE.md
Requires-Dist: numpy
Requires-Dist: scipy
Requires-Dist: matplotlib
